{
  "id": "consumer-utility",
  "title": "Consumer Theory & Utility Maximization",
  "category": "Microeconomics",
  "categoryPath": "microeconomics",
  "path": "articles/microeconomics/consumer-utility.html",
  "date": "2026-02-08",
  "description": "Exploring how consumers make choices under budget constraints to maximize utility using indifference curves and optimization techniques.",
  "tags": [
    "utility",
    "consumer theory",
    "optimization"
  ],
  "featured": false,
  "readTime": "10 min read",
  "author": "SimpleEconomy"
}
